LICENSE
MANIFEST.in
README.rst
setup.cfg
setup.py
versioneer.py
tests/__init__.py
tests/test_general.py
tpDcc/__init__.py
tpDcc/libs/__init__.py
tpDcc/libs/resources/__init__.py
tpDcc/libs/resources/__logging__.ini
tpDcc/libs/resources/__version__.py
tpDcc/libs/resources/_version.py
tpDcc/libs/resources/res.py
tpDcc/libs/resources/core/__init__.py
tpDcc/libs/resources/core/cache.py
tpDcc/libs/resources/core/color.py
tpDcc/libs/resources/core/icon.py
tpDcc/libs/resources/core/lib.py
tpDcc/libs/resources/core/pixmap.py
tpDcc/libs/resources/core/resource.py
tpDcc/libs/resources/core/style.py
tpDcc/libs/resources/core/theme.py
tpDcc/libs/resources/core/utils.py
tpDcc/libs/resources/fonts/fontawesome/fontawesome-webfont.ttf
tpDcc/libs/resources/fonts/opensans/LICENSE.txt
tpDcc/libs/resources/fonts/opensans/OpenSans-Bold.ttf
tpDcc/libs/resources/fonts/opensans/OpenSans-BoldItalic.ttf
tpDcc/libs/resources/fonts/opensans/OpenSans-ExtraBold.ttf
tpDcc/libs/resources/fonts/opensans/OpenSans-ExtraBoldItalic.ttf
tpDcc/libs/resources/fonts/opensans/OpenSans-Italic.ttf
tpDcc/libs/resources/fonts/opensans/OpenSans-Light.ttf
tpDcc/libs/resources/fonts/opensans/OpenSans-LightItalic.ttf
tpDcc/libs/resources/fonts/opensans/OpenSans-Regular.ttf
tpDcc/libs/resources/fonts/opensans/OpenSans-Semibold.ttf
tpDcc/libs/resources/fonts/opensans/OpenSans-SemiboldItalic.ttf
tpDcc/libs/resources/icons/black/add.png
tpDcc/libs/resources/icons/black/check_box_checked_black.png
tpDcc/libs/resources/icons/black/check_box_unchecked_black.png
tpDcc/libs/resources/icons/black/delete.png
tpDcc/libs/resources/icons/black/descending_sorting.png
tpDcc/libs/resources/icons/black/filter.png
tpDcc/libs/resources/icons/black/folder.png
tpDcc/libs/resources/icons/black/grid_view.png
tpDcc/libs/resources/icons/black/open_folder.png
tpDcc/libs/resources/icons/black/plus.png
tpDcc/libs/resources/icons/black/radio_button_checked_black.png
tpDcc/libs/resources/icons/black/radio_button_unchecked_black.png
tpDcc_libs_resources.egg-info/PKG-INFO
tpDcc_libs_resources.egg-info/SOURCES.txt
tpDcc_libs_resources.egg-info/dependency_links.txt
tpDcc_libs_resources.egg-info/not-zip-safe
tpDcc_libs_resources.egg-info/requires.txt
tpDcc_libs_resources.egg-info/top_level.txt