Metadata-Version: 2.1
Name: tpDcc-libs-resources
Version: 0.0.1
Summary: Repository that contains resources used by tpDcc framework.
Home-page: https://github.com/tpDcc/tpDcc-libs-resources
Author: Tomas Poveda
Author-email: tpovedatd@gmail.com
License: MIT
Platform: UNKNOWN
Provides-Extra: dev
Provides-Extra: test
